hoskerlatch/__init__.py
hoskerlatch/latcher.py
hoskerlatch/unlatcher.py
hoskerlatch-1.3.1.data/scripts/hoskerlatch
hoskerlatch-1.3.1.data/scripts/hoskerlatch-install-specials
hoskerlatch-1.3.1.data/scripts/hoskerunlatch
hoskerlatch-1.3.1.dist-info/LICENSE
hoskerlatch-1.3.1.dist-info/METADATA
hoskerlatch-1.3.1.dist-info/WHEEL
hoskerlatch-1.3.1.dist-info/top_level.txt
hoskerlatch-1.3.1.dist-info/RECORD
