Metadata-Version: 2.1
Name: hoskerlatch
Version: 1.3.1
Summary: Encrypt and decrypt folders to a medium standard of security
Home-page: https://github.com/tomhosker/hoskerlatch
Author: Tom Hosker
Author-email: tomdothosker@gmail.com
License: MIT
Platform: UNKNOWN
License-File: LICENSE
Requires-Dist: cryptography
Requires-Dist: hosker-utils
